cli/__init__.py
cli/cli.py
cli/commands/__init__.py
cli/commands/cmd_group.py
cli/commands/cmd_scripts.py
scripts/__init__.py
scripts/test.py
bumble_beem-0.0.1.dist-info/LICENSE
bumble_beem-0.0.1.dist-info/METADATA
bumble_beem-0.0.1.dist-info/WHEEL
bumble_beem-0.0.1.dist-info/entry_points.txt
bumble_beem-0.0.1.dist-info/top_level.txt
bumble_beem-0.0.1.dist-info/RECORD
